mcp_hexo_server/__init__.py
mcp_hexo_server/server.py
mcp_hexo_server/utils.py
mcp_hexo_server-0.1.0.dist-info/METADATA
mcp_hexo_server-0.1.0.dist-info/WHEEL
mcp_hexo_server-0.1.0.dist-info/entry_points.txt
mcp_hexo_server-0.1.0.dist-info/RECORD
